python_nano_bench/__init__.py
python_nano_bench/asm.py
python_nano_bench/nano_bench.py
python_nano_bench/cpuid/__init__.py
python_nano_bench/cpuid/cpuid.py
python_nano_bench/deps/nanoBench/cycleByCycle.py
python_nano_bench/deps/nanoBench/kernelNanoBench.py
python_nano_bench/deps/nanoBench/configs/convertIntelJSON.py
python_nano_bench/deps/nanoBench/tools/CPUID/cpuid.py
python_nano_bench/deps/nanoBench/tools/CacheAnalyzer/cacheGraph.py
python_nano_bench/deps/nanoBench/tools/CacheAnalyzer/cacheInfo.py
python_nano_bench/deps/nanoBench/tools/CacheAnalyzer/cacheLib.py
python_nano_bench/deps/nanoBench/tools/CacheAnalyzer/cacheSeq.py
python_nano_bench/deps/nanoBench/tools/CacheAnalyzer/cacheSim.py
python_nano_bench/deps/nanoBench/tools/CacheAnalyzer/hitMiss.py
python_nano_bench/deps/nanoBench/tools/CacheAnalyzer/permPolicy.py
python_nano_bench/deps/nanoBench/tools/CacheAnalyzer/replPolicy.py
python_nano_bench/deps/nanoBench/tools/CacheAnalyzer/setDueling.py
python_nano_bench/deps/nanoBench/tools/CacheAnalyzer/strideGraph.py
python_nano_bench/deps/nanoBench/tools/cpuBench/addAMDDocToXML.py
python_nano_bench/deps/nanoBench/tools/cpuBench/addDocToXML.py
python_nano_bench/deps/nanoBench/tools/cpuBench/addURLsToXML.py
python_nano_bench/deps/nanoBench/tools/cpuBench/compareMeasurementsToOther.py
python_nano_bench/deps/nanoBench/tools/cpuBench/compareXML.py
python_nano_bench/deps/nanoBench/tools/cpuBench/cpuBench.py
python_nano_bench/deps/nanoBench/tools/cpuBench/mergeXML.py
python_nano_bench/deps/nanoBench/tools/cpuBench/simpleHTMLTable.py
python_nano_bench/deps/nanoBench/tools/cpuBench/utils.py
python_nano_bench/deps/nanoBench/tools/cpuBench/x64_lib.py
python_nano_bench/elevate/__init__.py
python_nano_bench/elevate/posix.py
python_nano_bench/elevate/posix_loop.py
python_nano_bench/elevate/secrets.py
python_nano_bench/elevate/windows.py
python_nano_bench/test/__init__.py
python_nano_bench/test/asm.py
python_nano_bench/test/python_nano_bench.py
python_nano_bench-0.1.0.dist-info/licenses/LICENSE
python_nano_bench-0.1.0.dist-info/METADATA
python_nano_bench-0.1.0.dist-info/WHEEL
python_nano_bench-0.1.0.dist-info/entry_points.txt
python_nano_bench-0.1.0.dist-info/top_level.txt
python_nano_bench-0.1.0.dist-info/RECORD
